tp24/__init__.py
tp24/errors.py
tp24/internal.py
tp24/tools.py
tp24/model/colour.py
tp24/model/m_cmy.py
tp24/model/m_cmyk.py
tp24/model/m_hsl.py
tp24/model/m_hsv.py
tp24/model/m_rgb.py
tp24/model/web.json
tp24-1.0.dist-info/LICENSE
tp24-1.0.dist-info/METADATA
tp24-1.0.dist-info/WHEEL
tp24-1.0.dist-info/top_level.txt
tp24-1.0.dist-info/RECORD
