Metadata-Version: 2.1
Name: tp24
Version: 1.0
Summary: Python colour library
Home-page: https://github.com/iiiii7d/tp24
Author: 7d
Author-email: i.third.7d@protonmail.com
License: gpl-3.0
Download-URL: https://github.com/iiiii7d/tp24/archive/refs/tags/v1.0.tar.gz
Keywords: tp24,colour,color
Platform: UNKNOWN
Classifier: Development Status :: 5 - Production/Stable
Classifier: Intended Audience :: Developers
Classifier: License :: OSI Approved :: GNU General Public License v3 (GPLv3)
Classifier: Natural Language :: English
Classifier: Programming Language :: Python
Classifier: Programming Language :: Python :: 3
Classifier: Programming Language :: Python :: 3.7
Classifier: Programming Language :: Python :: 3.8
Classifier: Programming Language :: Python :: 3.9
Classifier: Programming Language :: Python :: 3.10
Classifier: Topic :: Utilities
Requires-Python: >=3.7
